{
  "swagger": "2.0",
  "info": {
    "version": "1.0",
    "title": "XenServer",
    "description": "TODO: Add Description",
    "contact": {}
  },
  "host": "192.168.100.35",
  "basePath": "/",
  "schemes": [
    "http"
  ],
  "consumes": [
    "application/json"
  ],
  "produces": [
    "application/json"
  ],
  "paths": {
    "/rrd_updates": {
      "get": {
        "description": "TODO: Add Description",
        "summary": "http://root:Citrix1@192.168.100.35/rrd_updates?start=1462838400&host=true",
        "tags": [
          "Misc"
        ],
        "operationId": "http://root:Citrix1@192.168.100.35/rrd_updates?start=1462838400&host=true",
        "deprecated": false,
        "produces": [
          "application/json"
        ],
        "parameters": [
          {
            "name": "start",
            "in": "query",
            "required": true,
            "type": "integer",
            "format": "int32",
            "description": ""
          },
          {
            "name": "host",
            "in": "query",
            "required": true,
            "type": "boolean",
            "description": ""
          }
        ],
        "responses": {
          "200": {
            "description": "",
            "headers": {}
          }
        }
      }
    }
  },
  "tags": [
    {
      "name": "Misc",
      "description": ""
    }
  ]
}